duk/__init__.py
duk/_version.py
duk/duk.py
duk-1.0.9.dist-info/licenses/LICENSE.txt
duk-1.0.9.dist-info/METADATA
duk-1.0.9.dist-info/WHEEL
duk-1.0.9.dist-info/entry_points.txt
duk-1.0.9.dist-info/top_level.txt
duk-1.0.9.dist-info/RECORD
