Metadata-Version: 2.4
Name: duk
Version: 1.0.9
Summary: Python wrapper around the du -ks command. It will show you a histogram of the disk usage in a directory
Author: Werner Van Geit
License-Expression: LGPL-3.0-or-later
Project-URL: homepage, https://github.com/wvangeit/duk
Classifier: Topic :: Utilities
Requires-Python: >=3.9
License-File: LICENSE.txt
Dynamic: license-file
